Metadata-Version: 2.1
Name: myylearn
Version: 0.2.5.7
Summary: An General Automated Machine Learning Framework
Home-page: https://github.com/DataCanvasIO/Hypernets
Author: DataCanvas Community
Author-email: yangjian@zetyun.com
License: Apache License 2.0
Platform: UNKNOWN
Classifier: Operating System :: OS Independent
Classifier: Intended Audience :: Developers
Classifier: Intended Audience :: Education
Classifier: Intended Audience :: Science/Research
Classifier: Programming Language :: Python
Classifier: Programming Language :: Python :: 3.6
Classifier: Programming Language :: Python :: 3.7
Classifier: Programming Language :: Python :: 3.8
Classifier: Programming Language :: Python :: 3.9
Classifier: Programming Language :: Python :: 3.10
Classifier: Topic :: Scientific/Engineering
Classifier: Topic :: Scientific/Engineering :: Artificial Intelligence
Classifier: Topic :: Software Development
Classifier: Topic :: Software Development :: Libraries
Classifier: Topic :: Software Development :: Libraries :: Python Modules
Requires-Python: >=3.6
Requires-Dist: numpy (>=1.16.5)
Requires-Dist: pandas (>=0.25.3)
Requires-Dist: scikit-learn (>=0.22.1)
Requires-Dist: scipy
Requires-Dist: lightgbm (>=2.2.0)
Requires-Dist: fsspec (>=0.8.0)
Requires-Dist: ipython
Requires-Dist: traitlets
Requires-Dist: featuretools (>=0.23.0)
Requires-Dist: XlsxWriter (>=3.0.2)
Requires-Dist: psutil
Requires-Dist: joblib
Requires-Dist: pyyaml
Requires-Dist: paramiko
Requires-Dist: requests
Requires-Dist: tornado
Requires-Dist: prettytable
Provides-Extra: all
Requires-Dist: cudf ; extra == 'all'
Requires-Dist: cuml ; extra == 'all'
Requires-Dist: cupy ; extra == 'all'
Requires-Dist: dask ; extra == 'all'
Requires-Dist: dask-ml ; extra == 'all'
Requires-Dist: distributed ; extra == 'all'
Requires-Dist: grpcio (>=1.24.0) ; extra == 'all'
Requires-Dist: hboard ; extra == 'all'
Requires-Dist: hboard-widget ; extra == 'all'
Requires-Dist: ipywidgets ; extra == 'all'
Requires-Dist: jieba ; extra == 'all'
Requires-Dist: jupyterlab ; extra == 'all'
Requires-Dist: jupyterlab-widgets ; extra == 'all'
Requires-Dist: paramiko ; extra == 'all'
Requires-Dist: protobuf (<4.0) ; extra == 'all'
Requires-Dist: pyarrow ; extra == 'all'
Requires-Dist: pynvml ; extra == 'all'
Requires-Dist: pytest ; extra == 'all'
Requires-Dist: pytest-cov ; extra == 'all'
Requires-Dist: python-geohash ; extra == 'all'
Requires-Dist: s3fs ; extra == 'all'
Provides-Extra: board
Requires-Dist: hboard ; extra == 'board'
Provides-Extra: cuml
Requires-Dist: cupy ; extra == 'cuml'
Requires-Dist: cudf ; extra == 'cuml'
Requires-Dist: cuml ; extra == 'cuml'
Requires-Dist: pynvml ; extra == 'cuml'
Provides-Extra: dask
Requires-Dist: dask ; extra == 'dask'
Requires-Dist: distributed ; extra == 'dask'
Requires-Dist: dask-ml ; extra == 'dask'
Provides-Extra: extra
Requires-Dist: paramiko ; extra == 'extra'
Requires-Dist: protobuf (<4.0) ; extra == 'extra'
Requires-Dist: grpcio (>=1.24.0) ; extra == 'extra'
Requires-Dist: s3fs ; extra == 'extra'
Requires-Dist: python-geohash ; extra == 'extra'
Requires-Dist: pyarrow ; extra == 'extra'
Provides-Extra: notebook
Requires-Dist: jupyterlab ; extra == 'notebook'
Requires-Dist: ipywidgets ; extra == 'notebook'
Requires-Dist: jupyterlab-widgets ; extra == 'notebook'
Requires-Dist: hboard-widget ; extra == 'notebook'
Provides-Extra: tests
Requires-Dist: pytest ; extra == 'tests'
Requires-Dist: pytest-cov ; extra == 'tests'
Provides-Extra: zhcn
Requires-Dist: jieba ; extra == 'zhcn'
